dataframe_optimizer/__init__.py
dataframe_optimizer/main.py
dataframe_optimizer-0.1.1.dist-info/METADATA
dataframe_optimizer-0.1.1.dist-info/WHEEL
dataframe_optimizer-0.1.1.dist-info/top_level.txt
dataframe_optimizer-0.1.1.dist-info/RECORD
