Metadata-Version: 2.1
Name: dataframe-optimizer
Version: 0.1.1
Summary: A Python package that give utils to optimize Pandas dataframes
Home-page: https://github.com/qrospars/dataframe-optimizer
Author: Quentin Rospars
Author-email: rospars.quentin@outlook.com
License: BSD 2-clause
Classifier: Programming Language :: Python :: 3
Classifier: License :: OSI Approved :: MIT License
Classifier: Operating System :: OS Independent
Requires-Dist: pandas
Requires-Dist: numpy
